mayini/__init__.py
mayini/base.py
mayini/metrics.py
mayini/tensor.py
mayini/utils.py
mayini/ml/__init__.py
mayini/ml/base.py
mayini/ml/metrics.py
mayini/ml/ensemble/__init__.py
mayini/ml/ensemble/bagging.py
mayini/ml/ensemble/boosting.py
mayini/ml/ensemble/voting.py
mayini/ml/supervised/__init__.py
mayini/ml/supervised/knn.py
mayini/ml/supervised/linear_models.py
mayini/ml/supervised/naive_bayes.py
mayini/ml/supervised/svm.py
mayini/ml/supervised/tree_models.py
mayini/ml/unsupervised/__init__.py
mayini/ml/unsupervised/anomaly.py
mayini/ml/unsupervised/clustering.py
mayini/ml/unsupervised/decomposition.py
mayini/neat/__init__.py
mayini/neat/activation.py
mayini/neat/config.py
mayini/neat/evaluator.py
mayini/neat/gene.py
mayini/neat/genome.py
mayini/neat/innovation.py
mayini/neat/neat.py
mayini/neat/network.py
mayini/neat/population.py
mayini/neat/reproduction.py
mayini/neat/species.py
mayini/neat/visualization.py
mayini/nn/__init__.py
mayini/nn/activations.py
mayini/nn/losses.py
mayini/nn/modules.py
mayini/nn/rnn.py
mayini/optim/__init__.py
mayini/optim/optimizers.py
mayini/preprocessing/__init__.py
mayini/preprocessing/autopreprocessor.py
mayini/preprocessing/base.py
mayini/preprocessing/outlier_detection.py
mayini/preprocessing/pipeline.py
mayini/preprocessing/type_conversion.py
mayini/preprocessing/categorical/__init__.py
mayini/preprocessing/categorical/encoders.py
mayini/preprocessing/categorical/target_encoding.py
mayini/preprocessing/feature_engineering/__init__.py
mayini/preprocessing/feature_engineering/extraction.py
mayini/preprocessing/feature_engineering/interactions.py
mayini/preprocessing/feature_engineering/polynomial.py
mayini/preprocessing/numerical/__init__.py
mayini/preprocessing/numerical/imputers.py
mayini/preprocessing/numerical/normalizers.py
mayini/preprocessing/numerical/scalers.py
mayini/preprocessing/selection/__init__.py
mayini/preprocessing/selection/correlation.py
mayini/preprocessing/selection/recursive.py
mayini_framework-0.6.4.dist-info/licenses/LICENSE
mayini_framework-0.6.4.dist-info/METADATA
mayini_framework-0.6.4.dist-info/WHEEL
mayini_framework-0.6.4.dist-info/top_level.txt
mayini_framework-0.6.4.dist-info/RECORD
