Metadata-Version: 2.4
Name: mayini-framework
Version: 0.6.4
Summary: A comprehensive deep learning framework built from scratch in Python with PyTorch-like API
Author-email: Abhishek Adari <abhishekadari85@gmail.com>
Maintainer-email: Giridhar palivela <nanipalivela830@gmail.com>
License: MIT
Project-URL: Homepage, https://github.com/907-bot-collab/mayini
Project-URL: Repository, https://github.com/907-bot-collab/mayini
Project-URL: Issues, https://github.com/907-bot-collab/mayini/issues
Project-URL: Documentation, https://github.com/907-bot-collab/mayini#readme
Project-URL: Changelog, https://github.com/907-bot-collab/mayini/releases
Keywords: deep-learning,neural-networks,machine-learning,framework,pytorch-like,autograd,automatic-differentiation,educational,ai,artificial-intelligence
Classifier: Development Status :: 3 - Alpha
Classifier: Intended Audience :: Developers
Classifier: Intended Audience :: Education
Classifier: Intended Audience :: Science/Research
Classifier: License :: OSI Approved :: MIT License
Classifier: Operating System :: OS Independent
Classifier: Programming Language :: Python :: 3
Classifier: Programming Language :: Python :: 3.8
Classifier: Programming Language :: Python :: 3.9
Classifier: Programming Language :: Python :: 3.10
Classifier: Programming Language :: Python :: 3.11
Classifier: Programming Language :: Python :: 3.12
Classifier: Topic :: Scientific/Engineering
Classifier: Topic :: Scientific/Engineering :: Artificial Intelligence
Classifier: Topic :: Scientific/Engineering :: Mathematics
Classifier: Topic :: Software Development :: Libraries
Classifier: Topic :: Software Development :: Libraries :: Python Modules
Classifier: Topic :: Education
Classifier: Typing :: Typed
Requires-Python: >=3.8
License-File: LICENSE
Requires-Dist: numpy>=1.21.0
Requires-Dist: scipy>=1.7.0
Requires-Dist: tqdm>=4.64.0
Provides-Extra: dev
Requires-Dist: pytest>=7.0.0; extra == "dev"
Requires-Dist: pytest-cov>=4.0.0; extra == "dev"
Requires-Dist: pytest-xdist>=3.0.0; extra == "dev"
Requires-Dist: black>=23.0.0; extra == "dev"
Requires-Dist: ruff>=0.1.0; extra == "dev"
Requires-Dist: mypy>=1.0.0; extra == "dev"
Requires-Dist: pre-commit>=3.0.0; extra == "dev"
Requires-Dist: ipython>=8.0.0; extra == "dev"
Requires-Dist: ipdb>=0.13.0; extra == "dev"
Provides-Extra: examples
Requires-Dist: matplotlib<4.0.0,>=3.5.0; extra == "examples"
Requires-Dist: seaborn<1.0.0,>=0.11.0; extra == "examples"
Requires-Dist: scikit-learn<2.0.0,>=1.1.0; extra == "examples"
Requires-Dist: pandas<3.0.0,>=1.4.0; extra == "examples"
Requires-Dist: jupyter>=1.0.0; extra == "examples"
Requires-Dist: notebook>=6.4.0; extra == "examples"
Provides-Extra: docs
Requires-Dist: sphinx>=5.0.0; extra == "docs"
Requires-Dist: sphinx-rtd-theme>=1.0.0; extra == "docs"
Requires-Dist: sphinx-autodoc-typehints>=1.19.0; extra == "docs"
Requires-Dist: myst-parser>=0.18.0; extra == "docs"
Provides-Extra: all
Requires-Dist: mayini-framework[dev,docs,examples]; extra == "all"
Dynamic: license-file
